MANIFEST.in
README.md
README.rst
setup.cfg
setup.py
Control_DB_date/Control_DB_date.py
Control_DB_date/__init__.py
Control_DB_date.egg-info/PKG-INFO
Control_DB_date.egg-info/SOURCES.txt
Control_DB_date.egg-info/dependency_links.txt
Control_DB_date.egg-info/requires.txt
Control_DB_date.egg-info/top_level.txt