Metadata-Version: 1.0
Name: Control-DB-date
Version: 1.5.0
Summary: get dbname from date and dbname , According to the monthly
Home-page: https://github.com/rfyiamcool
Author: rfyiamcool
Author-email: rfyiamcool@163.com
License: MIT
Platform: UNKNOWN
